django_static_dm_file_uploader/.DS_Store
django_static_dm_file_uploader/__init__.py
django_static_dm_file_uploader/admin.py
django_static_dm_file_uploader/apps.py
django_static_dm_file_uploader/models.py
django_static_dm_file_uploader/tests.py
django_static_dm_file_uploader/views.py
django_static_dm_file_uploader/migrations/__init__.py
django_static_dm_file_uploader/static/.DS_Store
django_static_dm_file_uploader/static/dm_file_uploader/AUTHORS.txt
django_static_dm_file_uploader/static/dm_file_uploader/LICENSE.txt
django_static_dm_file_uploader/static/dm_file_uploader/css/jquery.dm-uploader.min.css
django_static_dm_file_uploader/static/dm_file_uploader/js/jquery.dm-uploader.min.js
django_static_dm_file_uploader-1.0.2.3.dist-info/LICENSE
django_static_dm_file_uploader-1.0.2.3.dist-info/METADATA
django_static_dm_file_uploader-1.0.2.3.dist-info/WHEEL
django_static_dm_file_uploader-1.0.2.3.dist-info/top_level.txt
django_static_dm_file_uploader-1.0.2.3.dist-info/RECORD
