Metadata-Version: 2.1
Name: django-static-dm-file-uploader
Version: 1.0.2.3
Summary: Django application contain jquery-uploader static files.
Author: Yan MengYong
Maintainer: Yan MengYong
License: MIT
Keywords: django static extentions,django static dm-file-uploader
Classifier: Development Status :: 5 - Production/Stable
Classifier: Intended Audience :: Developers
Classifier: Topic :: Software Development :: Libraries :: Python Modules
Classifier: License :: OSI Approved :: MIT License
Classifier: Programming Language :: Python :: 3
Classifier: Programming Language :: Python :: 3 :: Only
Requires: django
License-File: LICENSE
Requires-Dist: django
